Metadata-Version: 2.1
Name: ForYou
Version: 0.1
Summary: Es un paquete para alguin especial
Home-page: https://github.com/CarlosGr10/ForYou.git
Author: Caros Garcia Garcia
Author-email: tigrecarlos1@gmail.com
License: MIT
Download-URL: https://github.com/CarlosGr10/ForYou.git/tarball/01
Platform: UNKNOWN
